[
  {
    "ClassName": "speed",
    "CaexPath": "AutomationML_BasicProperties.Physics_AttributeTypeLib/speed",
    "BasePath": null,
    "LibraryName": "AutomationML_BasicProperties.Physics_AttributeTypeLib",
    "LibraryVersion": "0.0.5",
    "AMLEdition": "AMLEd2",
    "ID": "374968f9-ea70-4383-86f5-7f647a6c3db6"
  },
  {
    "ClassName": "velocity",
    "CaexPath": "AutomationML_BasicProperties.Physics_AttributeTypeLib/velocity",
    "BasePath": "AutomationML_BasicProperties.Physics_AttributeTypeLib/speed",
    "LibraryName": "AutomationML_BasicProperties.Physics_AttributeTypeLib",
    "LibraryVersion": "0.0.5",
    "AMLEdition": "AMLEd2",
    "ID": "a6e05a5b-ed15-4e55-9d05-16f16895517d"
  },
  {
    "ClassName": "coordinate",
    "CaexPath": "AutomationML_BasicProperties.Physics_AttributeTypeLib/coordinate",
    "BasePath": null,
    "LibraryName": "AutomationML_BasicProperties.Physics_AttributeTypeLib",
    "LibraryVersion": "0.0.5",
    "AMLEdition": "AMLEd2",
    "ID": "7f408b6c-3fc2-4eb3-b6ef-0e60f532af88"
  },
  {
    "ClassName": "point",
    "CaexPath": "AutomationML_BasicProperties.Physics_AttributeTypeLib/point",
    "BasePath": null,
    "LibraryName": "AutomationML_BasicProperties.Physics_AttributeTypeLib",
    "LibraryVersion": "0.0.5",
    "AMLEdition": "AMLEd2",
    "ID": "4c71cf75-f583-4e3e-b75b-d06a531d3fdc"
  },
  {
    "ClassName": "temperature",
    "CaexPath": "AutomationML_BasicProperties.Physics_AttributeTypeLib/temperature",
    "BasePath": null,
    "LibraryName": "AutomationML_BasicProperties.Physics_AttributeTypeLib",
    "LibraryVersion": "0.0.5",
    "AMLEdition": "AMLEd2",
    "ID": "ae160881-21bc-406f-88d6-319ba60dbe66"
  },
  {
    "ClassName": "force",
    "CaexPath": "AutomationML_BasicProperties.Physics_AttributeTypeLib/force",
    "BasePath": null,
    "LibraryName": "AutomationML_BasicProperties.Physics_AttributeTypeLib",
    "LibraryVersion": "0.0.5",
    "AMLEdition": "AMLEd2",
    "ID": "d05cb017-7fdd-4ac3-9282-6a8cc6e8870b"
  },
  {
    "ClassName": "force",
    "CaexPath": "RD_RDBasicProperties.physicalProperties_AttributeTypeLib/force",
    "BasePath": null,
    "LibraryName": "RD_RDBasicProperties.physicalProperties_AttributeTypeLib",
    "LibraryVersion": "1.0.0",
    "AMLEdition": "AMLEd2",
    "ID": "2e34b2e2-c3df-4040-985f-d50429300884"
  },
  {
    "ClassName": "force",
    "CaexPath": "AutomationML_BasicProperties.physicalProperties_AttributeTypeLib/force",
    "BasePath": null,
    "LibraryName": "AutomationML_BasicProperties.physicalProperties_AttributeTypeLib",
    "LibraryVersion": "1.0.0",
    "AMLEdition": "AMLEd2",
    "ID": "2e34b2e2-c3df-4040-985f-d50429300884"
  },
  {
    "ClassName": "electricCurrent",
    "CaexPath": "AutomationML_BasicProperties.Electrics_AttributeTypeLib/electricCurrent",
    "BasePath": null,
    "LibraryName": "AutomationML_BasicProperties.Electrics_AttributeTypeLib",
    "LibraryVersion": "0.0.5",
    "AMLEdition": "AMLEd2",
    "ID": "0dd9f98d-8053-4977-82d8-fd79505001b5"
  },
  {
    "ClassName": "voltage",
    "CaexPath": "AutomationML_BasicProperties.Electrics_AttributeTypeLib/voltage",
    "BasePath": null,
    "LibraryName": "AutomationML_BasicProperties.Electrics_AttributeTypeLib",
    "LibraryVersion": "0.0.5",
    "AMLEdition": "AMLEd2",
    "ID": "d6d4770d-87d9-4d9c-9a8b-863c706ad86a"
  },
  {
    "ClassName": "resistance",
    "CaexPath": "AutomationML_BasicProperties.Electrics_AttributeTypeLib/resistance",
    "BasePath": null,
    "LibraryName": "AutomationML_BasicProperties.Electrics_AttributeTypeLib",
    "LibraryVersion": "0.0.5",
    "AMLEdition": "AMLEd2",
    "ID": "1c770ac0-9256-4ac9-a365-b47c94f43634"
  },
  {
    "ClassName": "resistance",
    "CaexPath": "AutomationML_DomainExtension.electrics_AttributeTypeLib/resistance",
    "BasePath": null,
    "LibraryName": "AutomationML_DomainExtension.electrics_AttributeTypeLib",
    "LibraryVersion": "1.0.0",
    "AMLEdition": "AMLEd2",
    "ID": "e9c8c746-8ef1-4da6-adcc-06ecda64c3f4"
  },
  {
    "ClassName": "capacity",
    "CaexPath": "AutomationML_BasicProperties.Electrics_AttributeTypeLib/capacity",
    "BasePath": null,
    "LibraryName": "AutomationML_BasicProperties.Electrics_AttributeTypeLib",
    "LibraryVersion": "0.0.5",
    "AMLEdition": "AMLEd2",
    "ID": "c075762b-c45a-46a5-ad5c-d1cf04ddda32"
  },
  {
    "ClassName": "mass",
    "CaexPath": "AutomationML_BasicProperties.Physics_AttributeTypeLib/mass",
    "BasePath": null,
    "LibraryName": "AutomationML_BasicProperties.Physics_AttributeTypeLib",
    "LibraryVersion": "0.0.5",
    "AMLEdition": "AMLEd2",
    "ID": "08c14034-6444-478a-8e7d-093b959318f7"
  },
  {
    "ClassName": "mass",
    "CaexPath": "RD_RDBasicProperties.physicalProperties_AttributeTypeLib/mass",
    "BasePath": null,
    "LibraryName": "RD_RDBasicProperties.physicalProperties_AttributeTypeLib",
    "LibraryVersion": "1.0.0",
    "AMLEdition": "AMLEd2",
    "ID": "7f4ee139-ca49-4dbf-9de4-2f6330d8683a"
  },
  {
    "ClassName": "mass",
    "CaexPath": "AutomationML_BasicProperties.physicalProperties_AttributeTypeLib/mass",
    "BasePath": null,
    "LibraryName": "AutomationML_BasicProperties.physicalProperties_AttributeTypeLib",
    "LibraryVersion": "1.0.0",
    "AMLEdition": "AMLEd2",
    "ID": "7f4ee139-ca49-4dbf-9de4-2f6330d8683a"
  },
  {
    "ClassName": "energy",
    "CaexPath": "AutomationML_BasicProperties.Physics_AttributeTypeLib/energy",
    "BasePath": null,
    "LibraryName": "AutomationML_BasicProperties.Physics_AttributeTypeLib",
    "LibraryVersion": "0.0.5",
    "AMLEdition": "AMLEd2",
    "ID": "0beb18d3-5252-47b4-bc6c-5e3edd1fe488"
  },
  {
    "ClassName": "power",
    "CaexPath": "AutomationML_BasicProperties.Physics_AttributeTypeLib/power",
    "BasePath": null,
    "LibraryName": "AutomationML_BasicProperties.Physics_AttributeTypeLib",
    "LibraryVersion": "0.0.5",
    "AMLEdition": "AMLEd2",
    "ID": "0bead0f8-5da0-4d23-90e0-21a4f211f9df"
  },
  {
    "ClassName": "dimension",
    "CaexPath": "AutomationML_BasicProperties.General_AttributeTypeLib/dimension",
    "BasePath": null,
    "LibraryName": "AutomationML_BasicProperties.General_AttributeTypeLib",
    "LibraryVersion": "0.0.5",
    "AMLEdition": "AMLEd2",
    "ID": "af8e216c-2ab4-4127-a211-bd79c3ded400"
  },
  {
    "ClassName": "length",
    "CaexPath": "AutomationML_BasicProperties.General_AttributeTypeLib/length",
    "BasePath": "AutomationML_BasicProperties.General_AttributeTypeLib/dimension",
    "LibraryName": "AutomationML_BasicProperties.General_AttributeTypeLib",
    "LibraryVersion": "0.0.5",
    "AMLEdition": "AMLEd2",
    "ID": "4b627153-c241-4df2-9fc6-016ac31e3b86"
  },
  {
    "ClassName": "width",
    "CaexPath": "AutomationML_BasicProperties.General_AttributeTypeLib/width",
    "BasePath": "AutomationML_BasicProperties.General_AttributeTypeLib/dimension",
    "LibraryName": "AutomationML_BasicProperties.General_AttributeTypeLib",
    "LibraryVersion": "0.0.5",
    "AMLEdition": "AMLEd2",
    "ID": "d07e2dd9-9441-4941-9472-ce724d125718"
  },
  {
    "ClassName": "height",
    "CaexPath": "AutomationML_BasicProperties.General_AttributeTypeLib/height",
    "BasePath": "AutomationML_BasicProperties.General_AttributeTypeLib/dimension",
    "LibraryName": "AutomationML_BasicProperties.General_AttributeTypeLib",
    "LibraryVersion": "0.0.5",
    "AMLEdition": "AMLEd2",
    "ID": "dc4295b5-8c1f-41da-aedc-910d69cb910c"
  },
  {
    "ClassName": "volume",
    "CaexPath": "AutomationML_BasicProperties.General_AttributeTypeLib/volume",
    "BasePath": null,
    "LibraryName": "AutomationML_BasicProperties.General_AttributeTypeLib",
    "LibraryVersion": "0.0.5",
    "AMLEdition": "AMLEd2",
    "ID": "adbf5614-aa39-4b6f-ab36-4bc4c0003816"
  },
  {
    "ClassName": "volume",
    "CaexPath": "RD_RDBasicProperties.physicalProperties_AttributeTypeLib/volume",
    "BasePath": null,
    "LibraryName": "RD_RDBasicProperties.physicalProperties_AttributeTypeLib",
    "LibraryVersion": "1.0.0",
    "AMLEdition": "AMLEd2",
    "ID": "cb904de1-28c4-4282-8206-358bdcb0af5d"
  },
  {
    "ClassName": "volume",
    "CaexPath": "AutomationML_BasicProperties.physicalProperties_AttributeTypeLib/volume",
    "BasePath": null,
    "LibraryName": "AutomationML_BasicProperties.physicalProperties_AttributeTypeLib",
    "LibraryVersion": "1.0.0",
    "AMLEdition": "AMLEd2",
    "ID": "cb904de1-28c4-4282-8206-358bdcb0af5d"
  },
  {
    "ClassName": "magneticFieldStrength",
    "CaexPath": "AutomationML_BasicProperties.Electrics_AttributeTypeLib/magneticFieldStrength",
    "BasePath": null,
    "LibraryName": "AutomationML_BasicProperties.Electrics_AttributeTypeLib",
    "LibraryVersion": "0.0.5",
    "AMLEdition": "AMLEd2",
    "ID": "55469615-1870-4652-8ce5-1dce4da259b1"
  },
  {
    "ClassName": "electricFieldStrength",
    "CaexPath": "AutomationML_BasicProperties.Electrics_AttributeTypeLib/electricFieldStrength",
    "BasePath": null,
    "LibraryName": "AutomationML_BasicProperties.Electrics_AttributeTypeLib",
    "LibraryVersion": "0.0.5",
    "AMLEdition": "AMLEd2",
    "ID": "d200d1fc-79d4-48b4-9786-7bf37b8bef17"
  },
  {
    "ClassName": "color",
    "CaexPath": "AutomationML_BasicProperties.Color_AttributeTypeLib/color",
    "BasePath": null,
    "LibraryName": "AutomationML_BasicProperties.Color_AttributeTypeLib",
    "LibraryVersion": "0.0.5",
    "AMLEdition": "AMLEd2",
    "ID": "76e133b5-839f-43d2-b195-8681e34af95f"
  },
  {
    "ClassName": "color",
    "CaexPath": "RD_RDBasicProperties.appearance_AttributeTypeLib/color",
    "BasePath": null,
    "LibraryName": "RD_RDBasicProperties.appearance_AttributeTypeLib",
    "LibraryVersion": "1.0.0",
    "AMLEdition": "AMLEd2",
    "ID": "daf161c4-35be-4d8e-9763-b3fc79bd3d12"
  },
  {
    "ClassName": "color",
    "CaexPath": "AutomationML_BasicProperties.appearance_AttributeTypeLib/color",
    "BasePath": null,
    "LibraryName": "AutomationML_BasicProperties.appearance_AttributeTypeLib",
    "LibraryVersion": "1.0.0",
    "AMLEdition": "AMLEd2",
    "ID": "daf161c4-35be-4d8e-9763-b3fc79bd3d12"
  },
  {
    "ClassName": "RAL",
    "CaexPath": "AutomationML_BasicProperties.Color_AttributeTypeLib/RAL",
    "BasePath": "AutomationML_BasicProperties.Color_AttributeTypeLib/color",
    "LibraryName": "AutomationML_BasicProperties.Color_AttributeTypeLib",
    "LibraryVersion": "0.0.5",
    "AMLEdition": "AMLEd2",
    "ID": "1917d508-35a2-4d37-80a2-981c4abfd7bf"
  },
  {
    "ClassName": "RGB",
    "CaexPath": "AutomationML_BasicProperties.Color_AttributeTypeLib/RGB",
    "BasePath": "AutomationML_BasicProperties.Color_AttributeTypeLib/color",
    "LibraryName": "AutomationML_BasicProperties.Color_AttributeTypeLib",
    "LibraryVersion": "0.0.5",
    "AMLEdition": "AMLEd2",
    "ID": "738ae261-331e-4534-837f-7a70c051068b"
  },
  {
    "ClassName": "work",
    "CaexPath": "AutomationML_BasicProperties.Physics_AttributeTypeLib/work",
    "BasePath": null,
    "LibraryName": "AutomationML_BasicProperties.Physics_AttributeTypeLib",
    "LibraryVersion": "0.0.5",
    "AMLEdition": "AMLEd2",
    "ID": "7e1375d5-3f55-4218-bf6c-d8cf69256355"
  },
  {
    "ClassName": "momentum",
    "CaexPath": "AutomationML_BasicProperties.Physics_AttributeTypeLib/momentum",
    "BasePath": null,
    "LibraryName": "AutomationML_BasicProperties.Physics_AttributeTypeLib",
    "LibraryVersion": "0.0.5",
    "AMLEdition": "AMLEd2",
    "ID": "202d96aa-055e-4e79-9e04-3a1546f91bf5"
  },
  {
    "ClassName": "staticPressure",
    "CaexPath": "AutomationML_BasicProperties.Physics_AttributeTypeLib/staticPressure",
    "BasePath": null,
    "LibraryName": "AutomationML_BasicProperties.Physics_AttributeTypeLib",
    "LibraryVersion": "0.0.5",
    "AMLEdition": "AMLEd2",
    "ID": "871513c2-8ac5-49e8-b16e-bed5100259dc"
  },
  {
    "ClassName": "frequency",
    "CaexPath": "AutomationML_BasicProperties.Physics_AttributeTypeLib/frequency",
    "BasePath": null,
    "LibraryName": "AutomationML_BasicProperties.Physics_AttributeTypeLib",
    "LibraryVersion": "0.0.5",
    "AMLEdition": "AMLEd2",
    "ID": "307c0099-18ed-4202-8d86-3dbfea2975af"
  },
  {
    "ClassName": "frequency",
    "CaexPath": "RD_RDBasicProperties.physicalProperties_AttributeTypeLib/frequency",
    "BasePath": null,
    "LibraryName": "RD_RDBasicProperties.physicalProperties_AttributeTypeLib",
    "LibraryVersion": "1.0.0",
    "AMLEdition": "AMLEd2",
    "ID": "6650816f-3b7c-480c-ba91-557cd31af4cb"
  },
  {
    "ClassName": "frequency",
    "CaexPath": "AutomationML_BasicProperties.physicalProperties_AttributeTypeLib/frequency",
    "BasePath": null,
    "LibraryName": "AutomationML_BasicProperties.physicalProperties_AttributeTypeLib",
    "LibraryVersion": "1.0.0",
    "AMLEdition": "AMLEd2",
    "ID": "6650816f-3b7c-480c-ba91-557cd31af4cb"
  },
  {
    "ClassName": "wavelength",
    "CaexPath": "AutomationML_BasicProperties.Physics_AttributeTypeLib/wavelength",
    "BasePath": null,
    "LibraryName": "AutomationML_BasicProperties.Physics_AttributeTypeLib",
    "LibraryVersion": "0.0.5",
    "AMLEdition": "AMLEd2",
    "ID": "62a2f5fa-a888-4d23-ba67-e82e5bf54463"
  },
  {
    "ClassName": "wavelength",
    "CaexPath": "RD_RDBasicProperties.physicalProperties_AttributeTypeLib/wavelength",
    "BasePath": null,
    "LibraryName": "RD_RDBasicProperties.physicalProperties_AttributeTypeLib",
    "LibraryVersion": "1.0.0",
    "AMLEdition": "AMLEd2",
    "ID": "ed9dffee-161b-43a5-831a-7c7377fd48a1"
  },
  {
    "ClassName": "wavelength",
    "CaexPath": "AutomationML_BasicProperties.physicalProperties_AttributeTypeLib/wavelength",
    "BasePath": null,
    "LibraryName": "AutomationML_BasicProperties.physicalProperties_AttributeTypeLib",
    "LibraryVersion": "1.0.0",
    "AMLEdition": "AMLEd2",
    "ID": "ed9dffee-161b-43a5-831a-7c7377fd48a1"
  },
  {
    "ClassName": "angularVelocity",
    "CaexPath": "AutomationML_BasicProperties.Physics_AttributeTypeLib/angularVelocity",
    "BasePath": null,
    "LibraryName": "AutomationML_BasicProperties.Physics_AttributeTypeLib",
    "LibraryVersion": "0.0.5",
    "AMLEdition": "AMLEd2",
    "ID": "b8027fc6-19cf-4fc9-a145-fc75365f20b0"
  },
  {
    "ClassName": "angularVelocity",
    "CaexPath": "RD_RDBasicProperties.kinematics_AttributeTypeLib/angularVelocity",
    "BasePath": null,
    "LibraryName": "RD_RDBasicProperties.kinematics_AttributeTypeLib",
    "LibraryVersion": "1.0.0",
    "AMLEdition": "AMLEd2",
    "ID": "49f7a4fc-5143-431e-b5f4-fb7cbe00c08e"
  },
  {
    "ClassName": "angularVelocity",
    "CaexPath": "AutomationML_BasicProperties.kinematics_AttributeTypeLib/angularVelocity",
    "BasePath": null,
    "LibraryName": "AutomationML_BasicProperties.kinematics_AttributeTypeLib",
    "LibraryVersion": "1.0.0",
    "AMLEdition": "AMLEd2",
    "ID": "49f7a4fc-5143-431e-b5f4-fb7cbe00c08e"
  },
  {
    "ClassName": "density",
    "CaexPath": "AutomationML_BasicProperties.Physics_AttributeTypeLib/density",
    "BasePath": null,
    "LibraryName": "AutomationML_BasicProperties.Physics_AttributeTypeLib",
    "LibraryVersion": "0.0.5",
    "AMLEdition": "AMLEd2",
    "ID": "4a4f19b3-4c86-4fb9-b3ec-2058dade0cb8"
  },
  {
    "ClassName": "density",
    "CaexPath": "RD_RDBasicProperties.physicalProperties_AttributeTypeLib/density",
    "BasePath": null,
    "LibraryName": "RD_RDBasicProperties.physicalProperties_AttributeTypeLib",
    "LibraryVersion": "1.0.0",
    "AMLEdition": "AMLEd2",
    "ID": "fc167316-6cbf-4bb5-9b17-fb2ce85dac9c"
  },
  {
    "ClassName": "density",
    "CaexPath": "AutomationML_BasicProperties.physicalProperties_AttributeTypeLib/density",
    "BasePath": null,
    "LibraryName": "AutomationML_BasicProperties.physicalProperties_AttributeTypeLib",
    "LibraryVersion": "1.0.0",
    "AMLEdition": "AMLEd2",
    "ID": "fc167316-6cbf-4bb5-9b17-fb2ce85dac9c"
  },
  {
    "ClassName": "specificHeatCapacity",
    "CaexPath": "AutomationML_BasicProperties.Physics_AttributeTypeLib/specificHeatCapacity",
    "BasePath": null,
    "LibraryName": "AutomationML_BasicProperties.Physics_AttributeTypeLib",
    "LibraryVersion": "0.0.5",
    "AMLEdition": "AMLEd2",
    "ID": "502183df-0598-4f58-a12b-b75c5d8bdd37"
  },
  {
    "ClassName": "acceleration",
    "CaexPath": "AutomationML_BasicProperties.Physics_AttributeTypeLib/acceleration",
    "BasePath": null,
    "LibraryName": "AutomationML_BasicProperties.Physics_AttributeTypeLib",
    "LibraryVersion": "0.0.5",
    "AMLEdition": "AMLEd2",
    "ID": "70300503-ebdd-47fe-bc4c-36b3a69f5d8a"
  },
  {
    "ClassName": "diameter",
    "CaexPath": "AutomationML_BasicProperties.General_AttributeTypeLib/diameter",
    "BasePath": "AutomationML_BasicProperties.General_AttributeTypeLib/dimension",
    "LibraryName": "AutomationML_BasicProperties.General_AttributeTypeLib",
    "LibraryVersion": "0.0.5",
    "AMLEdition": "AMLEd2",
    "ID": "8f944874-a415-4333-96be-52bb923a1c1e"
  },
  {
    "ClassName": "innerDiameter",
    "CaexPath": "AutomationML_BasicProperties.General_AttributeTypeLib/innerDiameter",
    "BasePath": "AutomationML_BasicProperties.General_AttributeTypeLib/diameter",
    "LibraryName": "AutomationML_BasicProperties.General_AttributeTypeLib",
    "LibraryVersion": "0.0.5",
    "AMLEdition": "AMLEd2",
    "ID": "c1b87b91-3000-4ea9-819f-7be94e0caa6e"
  },
  {
    "ClassName": "outerDiameter",
    "CaexPath": "AutomationML_BasicProperties.General_AttributeTypeLib/outerDiameter",
    "BasePath": "AutomationML_BasicProperties.General_AttributeTypeLib/diameter",
    "LibraryName": "AutomationML_BasicProperties.General_AttributeTypeLib",
    "LibraryVersion": "0.0.5",
    "AMLEdition": "AMLEd2",
    "ID": "59cf3916-3c18-4e20-ac94-da0d6b85f53e"
  },
  {
    "ClassName": "range",
    "CaexPath": "AutomationML_BasicProperties.General_AttributeTypeLib/range",
    "BasePath": "AutomationML_BasicProperties.General_AttributeTypeLib/dimension",
    "LibraryName": "AutomationML_BasicProperties.General_AttributeTypeLib",
    "LibraryVersion": "0.0.5",
    "AMLEdition": "AMLEd2",
    "ID": "ceea7ec9-88e7-442b-b174-4dbfe5dd268f"
  },
  {
    "ClassName": "CMYK",
    "CaexPath": "AutomationML_BasicProperties.Color_AttributeTypeLib/CMYK",
    "BasePath": "AutomationML_BasicProperties.Color_AttributeTypeLib/color",
    "LibraryName": "AutomationML_BasicProperties.Color_AttributeTypeLib",
    "LibraryVersion": "0.0.5",
    "AMLEdition": "AMLEd2",
    "ID": "f0fb949b-4b8f-400c-b5a8-665128e53868"
  },
  {
    "ClassName": "gravityAcceleration",
    "CaexPath": "AutomationML_BasicProperties.Physics_AttributeTypeLib/gravityAcceleration",
    "BasePath": "AutomationML_BasicProperties.Physics_AttributeTypeLib/acceleration",
    "LibraryName": "AutomationML_BasicProperties.Physics_AttributeTypeLib",
    "LibraryVersion": "0.0.5",
    "AMLEdition": "AMLEd2",
    "ID": "da90ed61-f752-4f09-8001-62c1391ebcf7"
  },
  {
    "ClassName": "distance",
    "CaexPath": "AutomationML_BasicProperties.General_AttributeTypeLib/distance",
    "BasePath": "AutomationML_BasicProperties.General_AttributeTypeLib/dimension",
    "LibraryName": "AutomationML_BasicProperties.General_AttributeTypeLib",
    "LibraryVersion": "0.0.5",
    "AMLEdition": "AMLEd2",
    "ID": "1932b62f-f31e-4332-87a0-2f77e1af2999"
  },
  {
    "ClassName": "laenge-Typ",
    "CaexPath": "HSPF_MasterClass_AttributeTypeLib/laenge-Typ",
    "BasePath": null,
    "LibraryName": "HSPF_MasterClass_AttributeTypeLib",
    "LibraryVersion": "1.0.0",
    "AMLEdition": "AMLEd2",
    "ID": "64b9aaef-c381-49b9-9f47-11ef8bc0eff9"
  },
  {
    "ClassName": "laenge-Typ",
    "CaexPath": "HSPF_MasterClass_AttributeTypeLib/laenge-Typ",
    "BasePath": null,
    "LibraryName": "HSPF_MasterClass_AttributeTypeLib",
    "LibraryVersion": "1.0.1",
    "AMLEdition": "AMLEd2",
    "ID": "64b9aaef-c381-49b9-9f47-11ef8bc0eff9"
  },
  {
    "ClassName": "laenge-Typ",
    "CaexPath": "HSPF_MasterClass_AttributeTypeLib/laenge-Typ",
    "BasePath": null,
    "LibraryName": "HSPF_MasterClass_AttributeTypeLib",
    "LibraryVersion": "1.0.2",
    "AMLEdition": "AMLEd2",
    "ID": "64b9aaef-c381-49b9-9f47-11ef8bc0eff9"
  },
  {
    "ClassName": "laenge-Typ",
    "CaexPath": "HSPF_MasterClass_AttributeTypeLib/laenge-Typ",
    "BasePath": null,
    "LibraryName": "HSPF_MasterClass_AttributeTypeLib",
    "LibraryVersion": "1.0.21",
    "AMLEdition": "AMLEd2",
    "ID": "64b9aaef-c381-49b9-9f47-11ef8bc0eff9"
  },
  {
    "ClassName": "laenge-Typ",
    "CaexPath": "HSPF_MasterClass_AttributeTypeLib/laenge-Typ",
    "BasePath": null,
    "LibraryName": "HSPF_MasterClass_AttributeTypeLib",
    "LibraryVersion": "1.0.5",
    "AMLEdition": "AMLEd2",
    "ID": "64b9aaef-c381-49b9-9f47-11ef8bc0eff9"
  },
  {
    "ClassName": "laenge-Typ",
    "CaexPath": "HSPF_MasterClass_AttributeTypeLib/laenge-Typ",
    "BasePath": null,
    "LibraryName": "HSPF_MasterClass_AttributeTypeLib",
    "LibraryVersion": "1.0.51",
    "AMLEdition": "AMLEd2",
    "ID": "64b9aaef-c381-49b9-9f47-11ef8bc0eff9"
  },
  {
    "ClassName": "laenge-Typ",
    "CaexPath": "HSPF_MasterClass_AttributeTypeLib/laenge-Typ",
    "BasePath": null,
    "LibraryName": "HSPF_MasterClass_AttributeTypeLib",
    "LibraryVersion": "1.0.6",
    "AMLEdition": "AMLEd2",
    "ID": "64b9aaef-c381-49b9-9f47-11ef8bc0eff9"
  },
  {
    "ClassName": "breite-Typ",
    "CaexPath": "HSPF_MasterClass_AttributeTypeLib/breite-Typ",
    "BasePath": null,
    "LibraryName": "HSPF_MasterClass_AttributeTypeLib",
    "LibraryVersion": "1.0.0",
    "AMLEdition": "AMLEd2",
    "ID": "e2b689ce-1f3c-4aa3-b485-f9b8245b25d3"
  },
  {
    "ClassName": "breite-Typ",
    "CaexPath": "HSPF_MasterClass_AttributeTypeLib/breite-Typ",
    "BasePath": null,
    "LibraryName": "HSPF_MasterClass_AttributeTypeLib",
    "LibraryVersion": "1.0.1",
    "AMLEdition": "AMLEd2",
    "ID": "e2b689ce-1f3c-4aa3-b485-f9b8245b25d3"
  },
  {
    "ClassName": "breite-Typ",
    "CaexPath": "HSPF_MasterClass_AttributeTypeLib/breite-Typ",
    "BasePath": null,
    "LibraryName": "HSPF_MasterClass_AttributeTypeLib",
    "LibraryVersion": "1.0.2",
    "AMLEdition": "AMLEd2",
    "ID": "e2b689ce-1f3c-4aa3-b485-f9b8245b25d3"
  },
  {
    "ClassName": "breite-Typ",
    "CaexPath": "HSPF_MasterClass_AttributeTypeLib/breite-Typ",
    "BasePath": null,
    "LibraryName": "HSPF_MasterClass_AttributeTypeLib",
    "LibraryVersion": "1.0.21",
    "AMLEdition": "AMLEd2",
    "ID": "e2b689ce-1f3c-4aa3-b485-f9b8245b25d3"
  },
  {
    "ClassName": "breite-Typ",
    "CaexPath": "HSPF_MasterClass_AttributeTypeLib/breite-Typ",
    "BasePath": null,
    "LibraryName": "HSPF_MasterClass_AttributeTypeLib",
    "LibraryVersion": "1.0.5",
    "AMLEdition": "AMLEd2",
    "ID": "e2b689ce-1f3c-4aa3-b485-f9b8245b25d3"
  },
  {
    "ClassName": "breite-Typ",
    "CaexPath": "HSPF_MasterClass_AttributeTypeLib/breite-Typ",
    "BasePath": null,
    "LibraryName": "HSPF_MasterClass_AttributeTypeLib",
    "LibraryVersion": "1.0.51",
    "AMLEdition": "AMLEd2",
    "ID": "e2b689ce-1f3c-4aa3-b485-f9b8245b25d3"
  },
  {
    "ClassName": "breite-Typ",
    "CaexPath": "HSPF_MasterClass_AttributeTypeLib/breite-Typ",
    "BasePath": null,
    "LibraryName": "HSPF_MasterClass_AttributeTypeLib",
    "LibraryVersion": "1.0.6",
    "AMLEdition": "AMLEd2",
    "ID": "e2b689ce-1f3c-4aa3-b485-f9b8245b25d3"
  },
  {
    "ClassName": "hoeheTyp",
    "CaexPath": "HSPF_MasterClass_AttributeTypeLib/hoeheTyp",
    "BasePath": null,
    "LibraryName": "HSPF_MasterClass_AttributeTypeLib",
    "LibraryVersion": "1.0.0",
    "AMLEdition": "AMLEd2",
    "ID": "dde31796-c974-4621-9db8-918305b2eb44"
  },
  {
    "ClassName": "hoeheTyp",
    "CaexPath": "HSPF_MasterClass_AttributeTypeLib/hoeheTyp",
    "BasePath": null,
    "LibraryName": "HSPF_MasterClass_AttributeTypeLib",
    "LibraryVersion": "1.0.1",
    "AMLEdition": "AMLEd2",
    "ID": "dde31796-c974-4621-9db8-918305b2eb44"
  },
  {
    "ClassName": "hoeheTyp",
    "CaexPath": "HSPF_MasterClass_AttributeTypeLib/hoeheTyp",
    "BasePath": null,
    "LibraryName": "HSPF_MasterClass_AttributeTypeLib",
    "LibraryVersion": "1.0.2",
    "AMLEdition": "AMLEd2",
    "ID": "dde31796-c974-4621-9db8-918305b2eb44"
  },
  {
    "ClassName": "hoeheTyp",
    "CaexPath": "HSPF_MasterClass_AttributeTypeLib/hoeheTyp",
    "BasePath": null,
    "LibraryName": "HSPF_MasterClass_AttributeTypeLib",
    "LibraryVersion": "1.0.21",
    "AMLEdition": "AMLEd2",
    "ID": "dde31796-c974-4621-9db8-918305b2eb44"
  },
  {
    "ClassName": "hoeheTyp",
    "CaexPath": "HSPF_MasterClass_AttributeTypeLib/hoeheTyp",
    "BasePath": null,
    "LibraryName": "HSPF_MasterClass_AttributeTypeLib",
    "LibraryVersion": "1.0.5",
    "AMLEdition": "AMLEd2",
    "ID": "dde31796-c974-4621-9db8-918305b2eb44"
  },
  {
    "ClassName": "hoeheTyp",
    "CaexPath": "HSPF_MasterClass_AttributeTypeLib/hoeheTyp",
    "BasePath": null,
    "LibraryName": "HSPF_MasterClass_AttributeTypeLib",
    "LibraryVersion": "1.0.51",
    "AMLEdition": "AMLEd2",
    "ID": "dde31796-c974-4621-9db8-918305b2eb44"
  },
  {
    "ClassName": "hoeheTyp",
    "CaexPath": "HSPF_MasterClass_AttributeTypeLib/hoeheTyp",
    "BasePath": null,
    "LibraryName": "HSPF_MasterClass_AttributeTypeLib",
    "LibraryVersion": "1.0.6",
    "AMLEdition": "AMLEd2",
    "ID": "dde31796-c974-4621-9db8-918305b2eb44"
  },
  {
    "ClassName": "vol",
    "CaexPath": "HSPF_MasterClass_AttributeTypeLib/vol",
    "BasePath": null,
    "LibraryName": "HSPF_MasterClass_AttributeTypeLib",
    "LibraryVersion": "1.0.6",
    "AMLEdition": "AMLEd2",
    "ID": "23665839-fd6c-4f20-aaca-6b81a44cae78"
  },
  {
    "ClassName": "laengeDKE",
    "CaexPath": "DKE_Basis-Merkmale.Geometrie_AttributeTypeLib/laengeDKE",
    "BasePath": null,
    "LibraryName": "DKE_Basis-Merkmale.Geometrie_AttributeTypeLib",
    "LibraryVersion": "1.0.0",
    "AMLEdition": "AMLEd2",
    "ID": "d1b50d6e-48a3-43dd-88ad-f3fc6f7c2585"
  },
  {
    "ClassName": "laengeDKE",
    "CaexPath": "DKE_Basis-Merkmale.Geometrie_AttributeTypeLib/laengeDKE",
    "BasePath": null,
    "LibraryName": "DKE_Basis-Merkmale.Geometrie_AttributeTypeLib",
    "LibraryVersion": "1.0.1",
    "AMLEdition": "AMLEd2",
    "ID": "d1b50d6e-48a3-43dd-88ad-f3fc6f7c2585"
  },
  {
    "ClassName": "breiteDKE",
    "CaexPath": "DKE_Basis-Merkmale.Geometrie_AttributeTypeLib/breiteDKE",
    "BasePath": null,
    "LibraryName": "DKE_Basis-Merkmale.Geometrie_AttributeTypeLib",
    "LibraryVersion": "1.0.1",
    "AMLEdition": "AMLEd2",
    "ID": "45b483e1-88b4-4ab6-8a2d-6a13783fa042"
  },
  {
    "ClassName": "electricalLoadCase",
    "CaexPath": "AutomationML_DomainExtension.electrics_AttributeTypeLib/electricalLoadCase",
    "BasePath": null,
    "LibraryName": "AutomationML_DomainExtension.electrics_AttributeTypeLib",
    "LibraryVersion": "1.0.0",
    "AMLEdition": "AMLEd2",
    "ID": "80cd14c2-d582-45fe-9492-48f5d2886621"
  },
  {
    "ClassName": "phaseCount",
    "CaexPath": "AutomationML_DomainExtension.electrics_AttributeTypeLib/phaseCount",
    "BasePath": null,
    "LibraryName": "AutomationML_DomainExtension.electrics_AttributeTypeLib",
    "LibraryVersion": "1.0.0",
    "AMLEdition": "AMLEd2",
    "ID": "f2f331f6-8d94-4c12-af64-829465168305"
  },
  {
    "ClassName": "powerFactor",
    "CaexPath": "AutomationML_DomainExtension.electrics_AttributeTypeLib/powerFactor",
    "BasePath": null,
    "LibraryName": "AutomationML_DomainExtension.electrics_AttributeTypeLib",
    "LibraryVersion": "1.0.0",
    "AMLEdition": "AMLEd2",
    "ID": "651da632-b0ec-4936-b992-e00e88ddfc75"
  },
  {
    "ClassName": "impedance",
    "CaexPath": "AutomationML_DomainExtension.electrics_AttributeTypeLib/impedance",
    "BasePath": null,
    "LibraryName": "AutomationML_DomainExtension.electrics_AttributeTypeLib",
    "LibraryVersion": "1.0.0",
    "AMLEdition": "AMLEd2",
    "ID": "1608fe20-8b89-455c-bac9-cc4eef715258"
  },
  {
    "ClassName": "capacitance",
    "CaexPath": "AutomationML_DomainExtension.electrics_AttributeTypeLib/capacitance",
    "BasePath": null,
    "LibraryName": "AutomationML_DomainExtension.electrics_AttributeTypeLib",
    "LibraryVersion": "1.0.0",
    "AMLEdition": "AMLEd2",
    "ID": "0c2604ab-bf31-4915-a1f4-09a43e7a2bb5"
  },
  {
    "ClassName": "inductance",
    "CaexPath": "AutomationML_DomainExtension.electrics_AttributeTypeLib/inductance",
    "BasePath": null,
    "LibraryName": "AutomationML_DomainExtension.electrics_AttributeTypeLib",
    "LibraryVersion": "1.0.0",
    "AMLEdition": "AMLEd2",
    "ID": "bc424155-4209-4ed6-9d17-ab487c50f6ba"
  },
  {
    "ClassName": "insulationResistance",
    "CaexPath": "AutomationML_DomainExtension.electrics_AttributeTypeLib/insulationResistance",
    "BasePath": null,
    "LibraryName": "AutomationML_DomainExtension.electrics_AttributeTypeLib",
    "LibraryVersion": "1.0.0",
    "AMLEdition": "AMLEd2",
    "ID": "1db4a9eb-66c7-4de0-8b47-1e72a66088f3"
  },
  {
    "ClassName": "dielectricStrength",
    "CaexPath": "AutomationML_DomainExtension.electrics_AttributeTypeLib/dielectricStrength",
    "BasePath": null,
    "LibraryName": "AutomationML_DomainExtension.electrics_AttributeTypeLib",
    "LibraryVersion": "1.0.0",
    "AMLEdition": "AMLEd2",
    "ID": "5ce1e351-8c74-4697-aae9-cd4bc5c4b4b5"
  },
  {
    "ClassName": "shortCircuitCurrent",
    "CaexPath": "AutomationML_DomainExtension.electrics_AttributeTypeLib/shortCircuitCurrent",
    "BasePath": null,
    "LibraryName": "AutomationML_DomainExtension.electrics_AttributeTypeLib",
    "LibraryVersion": "1.0.0",
    "AMLEdition": "AMLEd2",
    "ID": "1ab4a372-42fa-4b90-8e19-cf0c248e1ae0"
  },
  {
    "ClassName": "leakageCurrent",
    "CaexPath": "AutomationML_DomainExtension.electrics_AttributeTypeLib/leakageCurrent",
    "BasePath": null,
    "LibraryName": "AutomationML_DomainExtension.electrics_AttributeTypeLib",
    "LibraryVersion": "1.0.0",
    "AMLEdition": "AMLEd2",
    "ID": "9cc1aec3-ab6b-4691-8e69-0cfe45d4b919"
  },
  {
    "ClassName": "maximumVoltage",
    "CaexPath": "AutomationML_DomainExtension.electrics_AttributeTypeLib/maximumVoltage",
    "BasePath": null,
    "LibraryName": "AutomationML_DomainExtension.electrics_AttributeTypeLib",
    "LibraryVersion": "1.0.0",
    "AMLEdition": "AMLEd2",
    "ID": "b926be28-8d43-490d-8ff4-b197a2c9f7e7"
  },
  {
    "ClassName": "maximumCurrent",
    "CaexPath": "AutomationML_DomainExtension.electrics_AttributeTypeLib/maximumCurrent",
    "BasePath": null,
    "LibraryName": "AutomationML_DomainExtension.electrics_AttributeTypeLib",
    "LibraryVersion": "1.0.0",
    "AMLEdition": "AMLEd2",
    "ID": "10581962-bb33-4a3e-bf4d-5acf880fa1a3"
  },
  {
    "ClassName": "position",
    "CaexPath": "RD_RDBasicProperties.kinematics_AttributeTypeLib/position",
    "BasePath": null,
    "LibraryName": "RD_RDBasicProperties.kinematics_AttributeTypeLib",
    "LibraryVersion": "1.0.0",
    "AMLEdition": "AMLEd2",
    "ID": "854cca65-9d26-4910-a5e3-6c52edabc01a"
  },
  {
    "ClassName": "position",
    "CaexPath": "AutomationML_BasicProperties.kinematics_AttributeTypeLib/position",
    "BasePath": null,
    "LibraryName": "AutomationML_BasicProperties.kinematics_AttributeTypeLib",
    "LibraryVersion": "1.0.0",
    "AMLEdition": "AMLEd2",
    "ID": "854cca65-9d26-4910-a5e3-6c52edabc01a"
  },
  {
    "ClassName": "overallLength",
    "CaexPath": "RD_RDBasicProperties.physicalProperties_AttributeTypeLib/overallLength",
    "BasePath": null,
    "LibraryName": "RD_RDBasicProperties.physicalProperties_AttributeTypeLib",
    "LibraryVersion": "1.0.0",
    "AMLEdition": "AMLEd2",
    "ID": "0c01bfd5-4006-46b7-98aa-89c0cd8016e2"
  },
  {
    "ClassName": "overallLength",
    "CaexPath": "AutomationML_BasicProperties.physicalProperties_AttributeTypeLib/overallLength",
    "BasePath": null,
    "LibraryName": "AutomationML_BasicProperties.physicalProperties_AttributeTypeLib",
    "LibraryVersion": "1.0.0",
    "AMLEdition": "AMLEd2",
    "ID": "0c01bfd5-4006-46b7-98aa-89c0cd8016e2"
  },
  {
    "ClassName": "overallWidth",
    "CaexPath": "RD_RDBasicProperties.physicalProperties_AttributeTypeLib/overallWidth",
    "BasePath": null,
    "LibraryName": "RD_RDBasicProperties.physicalProperties_AttributeTypeLib",
    "LibraryVersion": "1.0.0",
    "AMLEdition": "AMLEd2",
    "ID": "8b6fe5b7-1f67-46b6-b0c3-81a2468b5f8b"
  },
  {
    "ClassName": "overallWidth",
    "CaexPath": "AutomationML_BasicProperties.physicalProperties_AttributeTypeLib/overallWidth",
    "BasePath": null,
    "LibraryName": "AutomationML_BasicProperties.physicalProperties_AttributeTypeLib",
    "LibraryVersion": "1.0.0",
    "AMLEdition": "AMLEd2",
    "ID": "8b6fe5b7-1f67-46b6-b0c3-81a2468b5f8b"
  },
  {
    "ClassName": "overallHeight",
    "CaexPath": "RD_RDBasicProperties.physicalProperties_AttributeTypeLib/overallHeight",
    "BasePath": null,
    "LibraryName": "RD_RDBasicProperties.physicalProperties_AttributeTypeLib",
    "LibraryVersion": "1.0.0",
    "AMLEdition": "AMLEd2",
    "ID": "5eed6c00-4955-40de-b8b8-c3c168b45ee2"
  },
  {
    "ClassName": "overallHeight",
    "CaexPath": "AutomationML_BasicProperties.physicalProperties_AttributeTypeLib/overallHeight",
    "BasePath": null,
    "LibraryName": "AutomationML_BasicProperties.physicalProperties_AttributeTypeLib",
    "LibraryVersion": "1.0.0",
    "AMLEdition": "AMLEd2",
    "ID": "5eed6c00-4955-40de-b8b8-c3c168b45ee2"
  },
  {
    "ClassName": "surfaceArea",
    "CaexPath": "RD_RDBasicProperties.physicalProperties_AttributeTypeLib/surfaceArea",
    "BasePath": null,
    "LibraryName": "RD_RDBasicProperties.physicalProperties_AttributeTypeLib",
    "LibraryVersion": "1.0.0",
    "AMLEdition": "AMLEd2",
    "ID": "2eda386d-466e-4527-a0b2-6308e4df2e0e"
  },
  {
    "ClassName": "surfaceArea",
    "CaexPath": "AutomationML_BasicProperties.physicalProperties_AttributeTypeLib/surfaceArea",
    "BasePath": null,
    "LibraryName": "AutomationML_BasicProperties.physicalProperties_AttributeTypeLib",
    "LibraryVersion": "1.0.0",
    "AMLEdition": "AMLEd2",
    "ID": "2eda386d-466e-4527-a0b2-6308e4df2e0e"
  },
  {
    "ClassName": "footprintArea",
    "CaexPath": "RD_RDBasicProperties.physicalProperties_AttributeTypeLib/footprintArea",
    "BasePath": null,
    "LibraryName": "RD_RDBasicProperties.physicalProperties_AttributeTypeLib",
    "LibraryVersion": "1.0.0",
    "AMLEdition": "AMLEd2",
    "ID": "a5f05e71-404e-400e-a802-f6b135fcd431"
  },
  {
    "ClassName": "footprintArea",
    "CaexPath": "AutomationML_BasicProperties.physicalProperties_AttributeTypeLib/footprintArea",
    "BasePath": null,
    "LibraryName": "AutomationML_BasicProperties.physicalProperties_AttributeTypeLib",
    "LibraryVersion": "1.0.0",
    "AMLEdition": "AMLEd2",
    "ID": "a5f05e71-404e-400e-a802-f6b135fcd431"
  },
  {
    "ClassName": "operatingTemperatureMin",
    "CaexPath": "RD_RDBasicProperties.environmentalConditions_AttributeTypeLib/operatingTemperatureMin",
    "BasePath": null,
    "LibraryName": "RD_RDBasicProperties.environmentalConditions_AttributeTypeLib",
    "LibraryVersion": "1.0.0",
    "AMLEdition": "AMLEd2",
    "ID": "6f5d1a57-0896-4ebd-863e-48ba46955571"
  },
  {
    "ClassName": "operatingTemperatureMin",
    "CaexPath": "AutomationML_BasicProperties.environmentalConditions_AttributeTypeLib/operatingTemperatureMin",
    "BasePath": null,
    "LibraryName": "AutomationML_BasicProperties.environmentalConditions_AttributeTypeLib",
    "LibraryVersion": "1.0.0",
    "AMLEdition": "AMLEd2",
    "ID": "6f5d1a57-0896-4ebd-863e-48ba46955571"
  },
  {
    "ClassName": "orientation",
    "CaexPath": "RD_RDBasicProperties.kinematics_AttributeTypeLib/orientation",
    "BasePath": null,
    "LibraryName": "RD_RDBasicProperties.kinematics_AttributeTypeLib",
    "LibraryVersion": "1.0.0",
    "AMLEdition": "AMLEd2",
    "ID": "aa0fd634-2fe7-4799-a696-b848d4d49031"
  },
  {
    "ClassName": "orientation",
    "CaexPath": "AutomationML_BasicProperties.kinematics_AttributeTypeLib/orientation",
    "BasePath": null,
    "LibraryName": "AutomationML_BasicProperties.kinematics_AttributeTypeLib",
    "LibraryVersion": "1.0.0",
    "AMLEdition": "AMLEd2",
    "ID": "aa0fd634-2fe7-4799-a696-b848d4d49031"
  },
  {
    "ClassName": "linearVelocity",
    "CaexPath": "RD_RDBasicProperties.kinematics_AttributeTypeLib/linearVelocity",
    "BasePath": null,
    "LibraryName": "RD_RDBasicProperties.kinematics_AttributeTypeLib",
    "LibraryVersion": "1.0.0",
    "AMLEdition": "AMLEd2",
    "ID": "7b1f7180-532f-4c94-85cb-a38ec867f81c"
  },
  {
    "ClassName": "linearVelocity",
    "CaexPath": "AutomationML_BasicProperties.kinematics_AttributeTypeLib/linearVelocity",
    "BasePath": null,
    "LibraryName": "AutomationML_BasicProperties.kinematics_AttributeTypeLib",
    "LibraryVersion": "1.0.0",
    "AMLEdition": "AMLEd2",
    "ID": "7b1f7180-532f-4c94-85cb-a38ec867f81c"
  },
  {
    "ClassName": "linearAcceleration",
    "CaexPath": "RD_RDBasicProperties.kinematics_AttributeTypeLib/linearAcceleration",
    "BasePath": null,
    "LibraryName": "RD_RDBasicProperties.kinematics_AttributeTypeLib",
    "LibraryVersion": "1.0.0",
    "AMLEdition": "AMLEd2",
    "ID": "2a91335c-8247-4079-ae2b-f34cae236310"
  },
  {
    "ClassName": "linearAcceleration",
    "CaexPath": "AutomationML_BasicProperties.kinematics_AttributeTypeLib/linearAcceleration",
    "BasePath": null,
    "LibraryName": "AutomationML_BasicProperties.kinematics_AttributeTypeLib",
    "LibraryVersion": "1.0.0",
    "AMLEdition": "AMLEd2",
    "ID": "2a91335c-8247-4079-ae2b-f34cae236310"
  },
  {
    "ClassName": "angularAcceleration",
    "CaexPath": "RD_RDBasicProperties.kinematics_AttributeTypeLib/angularAcceleration",
    "BasePath": null,
    "LibraryName": "RD_RDBasicProperties.kinematics_AttributeTypeLib",
    "LibraryVersion": "1.0.0",
    "AMLEdition": "AMLEd2",
    "ID": "707e9380-cdd1-4d35-aa2f-8485b9ac198c"
  },
  {
    "ClassName": "angularAcceleration",
    "CaexPath": "AutomationML_BasicProperties.kinematics_AttributeTypeLib/angularAcceleration",
    "BasePath": null,
    "LibraryName": "AutomationML_BasicProperties.kinematics_AttributeTypeLib",
    "LibraryVersion": "1.0.0",
    "AMLEdition": "AMLEd2",
    "ID": "707e9380-cdd1-4d35-aa2f-8485b9ac198c"
  },
  {
    "ClassName": "displacement",
    "CaexPath": "RD_RDBasicProperties.kinematics_AttributeTypeLib/displacement",
    "BasePath": null,
    "LibraryName": "RD_RDBasicProperties.kinematics_AttributeTypeLib",
    "LibraryVersion": "1.0.0",
    "AMLEdition": "AMLEd2",
    "ID": "596ae1ed-78d3-43a8-a1b5-f9020f6b0afd"
  },
  {
    "ClassName": "displacement",
    "CaexPath": "AutomationML_BasicProperties.kinematics_AttributeTypeLib/displacement",
    "BasePath": null,
    "LibraryName": "AutomationML_BasicProperties.kinematics_AttributeTypeLib",
    "LibraryVersion": "1.0.0",
    "AMLEdition": "AMLEd2",
    "ID": "596ae1ed-78d3-43a8-a1b5-f9020f6b0afd"
  },
  {
    "ClassName": "rotationAngle",
    "CaexPath": "RD_RDBasicProperties.kinematics_AttributeTypeLib/rotationAngle",
    "BasePath": null,
    "LibraryName": "RD_RDBasicProperties.kinematics_AttributeTypeLib",
    "LibraryVersion": "1.0.0",
    "AMLEdition": "AMLEd2",
    "ID": "5aaeeded-4a37-45b5-abff-9ec74c8f39bf"
  },
  {
    "ClassName": "rotationAngle",
    "CaexPath": "AutomationML_BasicProperties.kinematics_AttributeTypeLib/rotationAngle",
    "BasePath": null,
    "LibraryName": "AutomationML_BasicProperties.kinematics_AttributeTypeLib",
    "LibraryVersion": "1.0.0",
    "AMLEdition": "AMLEd2",
    "ID": "5aaeeded-4a37-45b5-abff-9ec74c8f39bf"
  },
  {
    "ClassName": "motionState",
    "CaexPath": "RD_RDBasicProperties.kinematics_AttributeTypeLib/motionState",
    "BasePath": null,
    "LibraryName": "RD_RDBasicProperties.kinematics_AttributeTypeLib",
    "LibraryVersion": "1.0.0",
    "AMLEdition": "AMLEd2",
    "ID": "8abb9554-34b9-4714-96b1-4865d4574123"
  },
  {
    "ClassName": "motionState",
    "CaexPath": "AutomationML_BasicProperties.kinematics_AttributeTypeLib/motionState",
    "BasePath": null,
    "LibraryName": "AutomationML_BasicProperties.kinematics_AttributeTypeLib",
    "LibraryVersion": "1.0.0",
    "AMLEdition": "AMLEd2",
    "ID": "8abb9554-34b9-4714-96b1-4865d4574123"
  },
  {
    "ClassName": "referenceFrame",
    "CaexPath": "RD_RDBasicProperties.kinematics_AttributeTypeLib/referenceFrame",
    "BasePath": null,
    "LibraryName": "RD_RDBasicProperties.kinematics_AttributeTypeLib",
    "LibraryVersion": "1.0.0",
    "AMLEdition": "AMLEd2",
    "ID": "22f8d891-c459-435b-b550-17b4aaf7bb6c"
  },
  {
    "ClassName": "referenceFrame",
    "CaexPath": "AutomationML_BasicProperties.kinematics_AttributeTypeLib/referenceFrame",
    "BasePath": null,
    "LibraryName": "AutomationML_BasicProperties.kinematics_AttributeTypeLib",
    "LibraryVersion": "1.0.0",
    "AMLEdition": "AMLEd2",
    "ID": "22f8d891-c459-435b-b550-17b4aaf7bb6c"
  },
  {
    "ClassName": "designLifetime",
    "CaexPath": "RD_RDBasicProperties.reliabilityAndLifetime_AttributeTypeLib/designLifetime",
    "BasePath": null,
    "LibraryName": "RD_RDBasicProperties.reliabilityAndLifetime_AttributeTypeLib",
    "LibraryVersion": "1.0.0",
    "AMLEdition": "AMLEd2",
    "ID": "47db6c63-eff5-41fe-a11e-5f014275eb5d"
  },
  {
    "ClassName": "designLifetime",
    "CaexPath": "AutomationML_BasicProperties.reliabilityAndLifetime_AttributeTypeLib/designLifetime",
    "BasePath": null,
    "LibraryName": "AutomationML_BasicProperties.reliabilityAndLifetime_AttributeTypeLib",
    "LibraryVersion": "1.0.0",
    "AMLEdition": "AMLEd2",
    "ID": "47db6c63-eff5-41fe-a11e-5f014275eb5d"
  },
  {
    "ClassName": "ratedPower",
    "CaexPath": "RD_RDBasicProperties.energyAndConsumption_AttributeTypeLib/ratedPower",
    "BasePath": null,
    "LibraryName": "RD_RDBasicProperties.energyAndConsumption_AttributeTypeLib",
    "LibraryVersion": "1.0.0",
    "AMLEdition": "AMLEd2",
    "ID": "c2a8582f-cfe3-4afc-b6d1-82c19b670e84"
  },
  {
    "ClassName": "ratedPower",
    "CaexPath": "AutomationML_BasicProperties.energyAndConsumption_AttributeTypeLib/ratedPower",
    "BasePath": null,
    "LibraryName": "AutomationML_BasicProperties.energyAndConsumption_AttributeTypeLib",
    "LibraryVersion": "1.0.0",
    "AMLEdition": "AMLEd2",
    "ID": "c2a8582f-cfe3-4afc-b6d1-82c19b670e84"
  },
  {
    "ClassName": "powerDemandNominal",
    "CaexPath": "RD_RDBasicProperties.energyAndConsumption_AttributeTypeLib/powerDemandNominal",
    "BasePath": null,
    "LibraryName": "RD_RDBasicProperties.energyAndConsumption_AttributeTypeLib",
    "LibraryVersion": "1.0.0",
    "AMLEdition": "AMLEd2",
    "ID": "fcdc65e0-9324-463a-a4b2-467a7d7f6c3f"
  },
  {
    "ClassName": "powerDemandNominal",
    "CaexPath": "AutomationML_BasicProperties.energyAndConsumption_AttributeTypeLib/powerDemandNominal",
    "BasePath": null,
    "LibraryName": "AutomationML_BasicProperties.energyAndConsumption_AttributeTypeLib",
    "LibraryVersion": "1.0.0",
    "AMLEdition": "AMLEd2",
    "ID": "fcdc65e0-9324-463a-a4b2-467a7d7f6c3f"
  },
  {
    "ClassName": "powerDemandMin",
    "CaexPath": "RD_RDBasicProperties.energyAndConsumption_AttributeTypeLib/powerDemandMin",
    "BasePath": null,
    "LibraryName": "RD_RDBasicProperties.energyAndConsumption_AttributeTypeLib",
    "LibraryVersion": "1.0.0",
    "AMLEdition": "AMLEd2",
    "ID": "2fbff1f1-49ad-465b-abf3-9bf5f1f163dd"
  },
  {
    "ClassName": "powerDemandMin",
    "CaexPath": "AutomationML_BasicProperties.energyAndConsumption_AttributeTypeLib/powerDemandMin",
    "BasePath": null,
    "LibraryName": "AutomationML_BasicProperties.energyAndConsumption_AttributeTypeLib",
    "LibraryVersion": "1.0.0",
    "AMLEdition": "AMLEd2",
    "ID": "2fbff1f1-49ad-465b-abf3-9bf5f1f163dd"
  },
  {
    "ClassName": "secondaryColor",
    "CaexPath": "RD_RDBasicProperties.appearance_AttributeTypeLib/secondaryColor",
    "BasePath": null,
    "LibraryName": "RD_RDBasicProperties.appearance_AttributeTypeLib",
    "LibraryVersion": "1.0.0",
    "AMLEdition": "AMLEd2",
    "ID": "35194361-91a4-4c07-8482-5f4c1dd7b715"
  },
  {
    "ClassName": "secondaryColor",
    "CaexPath": "AutomationML_BasicProperties.appearance_AttributeTypeLib/secondaryColor",
    "BasePath": null,
    "LibraryName": "AutomationML_BasicProperties.appearance_AttributeTypeLib",
    "LibraryVersion": "1.0.0",
    "AMLEdition": "AMLEd2",
    "ID": "35194361-91a4-4c07-8482-5f4c1dd7b715"
  },
  {
    "ClassName": "surfaceFinish",
    "CaexPath": "RD_RDBasicProperties.appearance_AttributeTypeLib/surfaceFinish",
    "BasePath": null,
    "LibraryName": "RD_RDBasicProperties.appearance_AttributeTypeLib",
    "LibraryVersion": "1.0.0",
    "AMLEdition": "AMLEd2",
    "ID": "e091b64d-0071-4900-9edf-b3d32942310b"
  },
  {
    "ClassName": "surfaceFinish",
    "CaexPath": "AutomationML_BasicProperties.appearance_AttributeTypeLib/surfaceFinish",
    "BasePath": null,
    "LibraryName": "AutomationML_BasicProperties.appearance_AttributeTypeLib",
    "LibraryVersion": "1.0.0",
    "AMLEdition": "AMLEd2",
    "ID": "e091b64d-0071-4900-9edf-b3d32942310b"
  },
  {
    "ClassName": "surfaceTexture",
    "CaexPath": "RD_RDBasicProperties.appearance_AttributeTypeLib/surfaceTexture",
    "BasePath": null,
    "LibraryName": "RD_RDBasicProperties.appearance_AttributeTypeLib",
    "LibraryVersion": "1.0.0",
    "AMLEdition": "AMLEd2",
    "ID": "886a7ffe-36b1-48c3-b54c-ba957e54babc"
  },
  {
    "ClassName": "surfaceTexture",
    "CaexPath": "AutomationML_BasicProperties.appearance_AttributeTypeLib/surfaceTexture",
    "BasePath": null,
    "LibraryName": "AutomationML_BasicProperties.appearance_AttributeTypeLib",
    "LibraryVersion": "1.0.0",
    "AMLEdition": "AMLEd2",
    "ID": "886a7ffe-36b1-48c3-b54c-ba957e54babc"
  },
  {
    "ClassName": "materialAppearance",
    "CaexPath": "RD_RDBasicProperties.appearance_AttributeTypeLib/materialAppearance",
    "BasePath": null,
    "LibraryName": "RD_RDBasicProperties.appearance_AttributeTypeLib",
    "LibraryVersion": "1.0.0",
    "AMLEdition": "AMLEd2",
    "ID": "4858c504-2da5-41ae-af52-ca08e29e548b"
  },
  {
    "ClassName": "materialAppearance",
    "CaexPath": "AutomationML_BasicProperties.appearance_AttributeTypeLib/materialAppearance",
    "BasePath": null,
    "LibraryName": "AutomationML_BasicProperties.appearance_AttributeTypeLib",
    "LibraryVersion": "1.0.0",
    "AMLEdition": "AMLEd2",
    "ID": "4858c504-2da5-41ae-af52-ca08e29e548b"
  },
  {
    "ClassName": "coatingType",
    "CaexPath": "RD_RDBasicProperties.appearance_AttributeTypeLib/coatingType",
    "BasePath": null,
    "LibraryName": "RD_RDBasicProperties.appearance_AttributeTypeLib",
    "LibraryVersion": "1.0.0",
    "AMLEdition": "AMLEd2",
    "ID": "efad251b-6f6c-40ac-9b99-443e1fb05398"
  },
  {
    "ClassName": "coatingType",
    "CaexPath": "AutomationML_BasicProperties.appearance_AttributeTypeLib/coatingType",
    "BasePath": null,
    "LibraryName": "AutomationML_BasicProperties.appearance_AttributeTypeLib",
    "LibraryVersion": "1.0.0",
    "AMLEdition": "AMLEd2",
    "ID": "efad251b-6f6c-40ac-9b99-443e1fb05398"
  },
  {
    "ClassName": "labeling",
    "CaexPath": "RD_RDBasicProperties.appearance_AttributeTypeLib/labeling",
    "BasePath": null,
    "LibraryName": "RD_RDBasicProperties.appearance_AttributeTypeLib",
    "LibraryVersion": "1.0.0",
    "AMLEdition": "AMLEd2",
    "ID": "778bc2b8-40dc-4a65-bb65-ba01f3433ae9"
  },
  {
    "ClassName": "labeling",
    "CaexPath": "AutomationML_BasicProperties.appearance_AttributeTypeLib/labeling",
    "BasePath": null,
    "LibraryName": "AutomationML_BasicProperties.appearance_AttributeTypeLib",
    "LibraryVersion": "1.0.0",
    "AMLEdition": "AMLEd2",
    "ID": "778bc2b8-40dc-4a65-bb65-ba01f3433ae9"
  },
  {
    "ClassName": "branding",
    "CaexPath": "RD_RDBasicProperties.appearance_AttributeTypeLib/branding",
    "BasePath": null,
    "LibraryName": "RD_RDBasicProperties.appearance_AttributeTypeLib",
    "LibraryVersion": "1.0.0",
    "AMLEdition": "AMLEd2",
    "ID": "d97848e4-82b6-4209-85bb-f55e5da2374a"
  },
  {
    "ClassName": "branding",
    "CaexPath": "AutomationML_BasicProperties.appearance_AttributeTypeLib/branding",
    "BasePath": null,
    "LibraryName": "AutomationML_BasicProperties.appearance_AttributeTypeLib",
    "LibraryVersion": "1.0.0",
    "AMLEdition": "AMLEd2",
    "ID": "d97848e4-82b6-4209-85bb-f55e5da2374a"
  },
  {
    "ClassName": "symbolMarking",
    "CaexPath": "RD_RDBasicProperties.appearance_AttributeTypeLib/symbolMarking",
    "BasePath": null,
    "LibraryName": "RD_RDBasicProperties.appearance_AttributeTypeLib",
    "LibraryVersion": "1.0.0",
    "AMLEdition": "AMLEd2",
    "ID": "3f6bab5e-4aad-48f0-a6f3-eae231e606cc"
  },
  {
    "ClassName": "symbolMarking",
    "CaexPath": "AutomationML_BasicProperties.appearance_AttributeTypeLib/symbolMarking",
    "BasePath": null,
    "LibraryName": "AutomationML_BasicProperties.appearance_AttributeTypeLib",
    "LibraryVersion": "1.0.0",
    "AMLEdition": "AMLEd2",
    "ID": "3f6bab5e-4aad-48f0-a6f3-eae231e606cc"
  },
  {
    "ClassName": "illuminationColor",
    "CaexPath": "RD_RDBasicProperties.appearance_AttributeTypeLib/illuminationColor",
    "BasePath": null,
    "LibraryName": "RD_RDBasicProperties.appearance_AttributeTypeLib",
    "LibraryVersion": "1.0.0",
    "AMLEdition": "AMLEd2",
    "ID": "cd181b18-8bc9-4142-80ae-36363a9e4452"
  },
  {
    "ClassName": "illuminationColor",
    "CaexPath": "AutomationML_BasicProperties.appearance_AttributeTypeLib/illuminationColor",
    "BasePath": null,
    "LibraryName": "AutomationML_BasicProperties.appearance_AttributeTypeLib",
    "LibraryVersion": "1.0.0",
    "AMLEdition": "AMLEd2",
    "ID": "cd181b18-8bc9-4142-80ae-36363a9e4452"
  },
  {
    "ClassName": "appearanceVariant",
    "CaexPath": "RD_RDBasicProperties.appearance_AttributeTypeLib/appearanceVariant",
    "BasePath": null,
    "LibraryName": "RD_RDBasicProperties.appearance_AttributeTypeLib",
    "LibraryVersion": "1.0.0",
    "AMLEdition": "AMLEd2",
    "ID": "95cce0cd-fbb6-480b-8a45-9ad08e18c828"
  },
  {
    "ClassName": "appearanceVariant",
    "CaexPath": "AutomationML_BasicProperties.appearance_AttributeTypeLib/appearanceVariant",
    "BasePath": null,
    "LibraryName": "AutomationML_BasicProperties.appearance_AttributeTypeLib",
    "LibraryVersion": "1.0.0",
    "AMLEdition": "AMLEd2",
    "ID": "95cce0cd-fbb6-480b-8a45-9ad08e18c828"
  },
  {
    "ClassName": "visibilityClass",
    "CaexPath": "RD_RDBasicProperties.appearance_AttributeTypeLib/visibilityClass",
    "BasePath": null,
    "LibraryName": "RD_RDBasicProperties.appearance_AttributeTypeLib",
    "LibraryVersion": "1.0.0",
    "AMLEdition": "AMLEd2",
    "ID": "f18ab5e9-68f2-451d-a29c-0b4c948f2426"
  },
  {
    "ClassName": "visibilityClass",
    "CaexPath": "AutomationML_BasicProperties.appearance_AttributeTypeLib/visibilityClass",
    "BasePath": null,
    "LibraryName": "AutomationML_BasicProperties.appearance_AttributeTypeLib",
    "LibraryVersion": "1.0.0",
    "AMLEdition": "AMLEd2",
    "ID": "f18ab5e9-68f2-451d-a29c-0b4c948f2426"
  },
  {
    "ClassName": "meanTimeBetweenFailures",
    "CaexPath": "RD_RDBasicProperties.reliabilityAndLifetime_AttributeTypeLib/meanTimeBetweenFailures",
    "BasePath": null,
    "LibraryName": "RD_RDBasicProperties.reliabilityAndLifetime_AttributeTypeLib",
    "LibraryVersion": "1.0.0",
    "AMLEdition": "AMLEd2",
    "ID": "ca31add5-ca43-4566-99d4-927fb5a426fe"
  },
  {
    "ClassName": "meanTimeBetweenFailures",
    "CaexPath": "AutomationML_BasicProperties.reliabilityAndLifetime_AttributeTypeLib/meanTimeBetweenFailures",
    "BasePath": null,
    "LibraryName": "AutomationML_BasicProperties.reliabilityAndLifetime_AttributeTypeLib",
    "LibraryVersion": "1.0.0",
    "AMLEdition": "AMLEd2",
    "ID": "ca31add5-ca43-4566-99d4-927fb5a426fe"
  },
  {
    "ClassName": "operatingTemperatureMax",
    "CaexPath": "RD_RDBasicProperties.environmentalConditions_AttributeTypeLib/operatingTemperatureMax",
    "BasePath": null,
    "LibraryName": "RD_RDBasicProperties.environmentalConditions_AttributeTypeLib",
    "LibraryVersion": "1.0.0",
    "AMLEdition": "AMLEd2",
    "ID": "09616d9e-73f2-4d62-8a25-f7eaba353b68"
  },
  {
    "ClassName": "operatingTemperatureMax",
    "CaexPath": "AutomationML_BasicProperties.environmentalConditions_AttributeTypeLib/operatingTemperatureMax",
    "BasePath": null,
    "LibraryName": "AutomationML_BasicProperties.environmentalConditions_AttributeTypeLib",
    "LibraryVersion": "1.0.0",
    "AMLEdition": "AMLEd2",
    "ID": "09616d9e-73f2-4d62-8a25-f7eaba353b68"
  },
  {
    "ClassName": "storageTemperatureMin",
    "CaexPath": "RD_RDBasicProperties.environmentalConditions_AttributeTypeLib/storageTemperatureMin",
    "BasePath": null,
    "LibraryName": "RD_RDBasicProperties.environmentalConditions_AttributeTypeLib",
    "LibraryVersion": "1.0.0",
    "AMLEdition": "AMLEd2",
    "ID": "f4a4a279-5cb9-4c6d-9306-d07fcf26c59b"
  },
  {
    "ClassName": "storageTemperatureMin",
    "CaexPath": "AutomationML_BasicProperties.environmentalConditions_AttributeTypeLib/storageTemperatureMin",
    "BasePath": null,
    "LibraryName": "AutomationML_BasicProperties.environmentalConditions_AttributeTypeLib",
    "LibraryVersion": "1.0.0",
    "AMLEdition": "AMLEd2",
    "ID": "f4a4a279-5cb9-4c6d-9306-d07fcf26c59b"
  },
  {
    "ClassName": "storageTemperatureMax",
    "CaexPath": "RD_RDBasicProperties.environmentalConditions_AttributeTypeLib/storageTemperatureMax",
    "BasePath": null,
    "LibraryName": "RD_RDBasicProperties.environmentalConditions_AttributeTypeLib",
    "LibraryVersion": "1.0.0",
    "AMLEdition": "AMLEd2",
    "ID": "b84c6b31-68bf-45bb-ad5a-8041af29f2cb"
  },
  {
    "ClassName": "storageTemperatureMax",
    "CaexPath": "AutomationML_BasicProperties.environmentalConditions_AttributeTypeLib/storageTemperatureMax",
    "BasePath": null,
    "LibraryName": "AutomationML_BasicProperties.environmentalConditions_AttributeTypeLib",
    "LibraryVersion": "1.0.0",
    "AMLEdition": "AMLEd2",
    "ID": "b84c6b31-68bf-45bb-ad5a-8041af29f2cb"
  },
  {
    "ClassName": "relativeHumidityMin",
    "CaexPath": "RD_RDBasicProperties.environmentalConditions_AttributeTypeLib/relativeHumidityMin",
    "BasePath": null,
    "LibraryName": "RD_RDBasicProperties.environmentalConditions_AttributeTypeLib",
    "LibraryVersion": "1.0.0",
    "AMLEdition": "AMLEd2",
    "ID": "f6359b1a-4f41-4a85-842d-81cd4946fcb1"
  },
  {
    "ClassName": "relativeHumidityMin",
    "CaexPath": "AutomationML_BasicProperties.environmentalConditions_AttributeTypeLib/relativeHumidityMin",
    "BasePath": null,
    "LibraryName": "AutomationML_BasicProperties.environmentalConditions_AttributeTypeLib",
    "LibraryVersion": "1.0.0",
    "AMLEdition": "AMLEd2",
    "ID": "f6359b1a-4f41-4a85-842d-81cd4946fcb1"
  },
  {
    "ClassName": "relativeHumidityMax",
    "CaexPath": "RD_RDBasicProperties.environmentalConditions_AttributeTypeLib/relativeHumidityMax",
    "BasePath": null,
    "LibraryName": "RD_RDBasicProperties.environmentalConditions_AttributeTypeLib",
    "LibraryVersion": "1.0.0",
    "AMLEdition": "AMLEd2",
    "ID": "0e09869a-536c-4f47-a3aa-74d192cfd02b"
  },
  {
    "ClassName": "relativeHumidityMax",
    "CaexPath": "AutomationML_BasicProperties.environmentalConditions_AttributeTypeLib/relativeHumidityMax",
    "BasePath": null,
    "LibraryName": "AutomationML_BasicProperties.environmentalConditions_AttributeTypeLib",
    "LibraryVersion": "1.0.0",
    "AMLEdition": "AMLEd2",
    "ID": "0e09869a-536c-4f47-a3aa-74d192cfd02b"
  },
  {
    "ClassName": "id",
    "CaexPath": "RD_RDBasicProperties_AttributeTypeLib/id",
    "BasePath": null,
    "LibraryName": "RD_RDBasicProperties_AttributeTypeLib",
    "LibraryVersion": "1.0.0",
    "AMLEdition": "AMLEd2",
    "ID": "3358e218-b893-4ba7-aafc-fb7b5e493acb"
  },
  {
    "ClassName": "id",
    "CaexPath": "AutomationML_BasicProperties.identification_AttributeTypeLib/id",
    "BasePath": null,
    "LibraryName": "AutomationML_BasicProperties.identification_AttributeTypeLib",
    "LibraryVersion": "1.0.0",
    "AMLEdition": "AMLEd2",
    "ID": "3358e218-b893-4ba7-aafc-fb7b5e493acb"
  },
  {
    "ClassName": "idShort",
    "CaexPath": "RD_RDBasicProperties_AttributeTypeLib/idShort",
    "BasePath": null,
    "LibraryName": "RD_RDBasicProperties_AttributeTypeLib",
    "LibraryVersion": "1.0.0",
    "AMLEdition": "AMLEd2",
    "ID": "8defc9da-86a1-48a9-a139-d49ea42aaa80"
  },
  {
    "ClassName": "idShort",
    "CaexPath": "AutomationML_BasicProperties.identification_AttributeTypeLib/idShort",
    "BasePath": null,
    "LibraryName": "AutomationML_BasicProperties.identification_AttributeTypeLib",
    "LibraryVersion": "1.0.0",
    "AMLEdition": "AMLEd2",
    "ID": "8defc9da-86a1-48a9-a139-d49ea42aaa80"
  },
  {
    "ClassName": "semanticId",
    "CaexPath": "RD_RDBasicProperties_AttributeTypeLib/semanticId",
    "BasePath": null,
    "LibraryName": "RD_RDBasicProperties_AttributeTypeLib",
    "LibraryVersion": "1.0.0",
    "AMLEdition": "AMLEd2",
    "ID": "3804f0c7-f80c-461f-930e-5d519f385ec5"
  },
  {
    "ClassName": "semanticId",
    "CaexPath": "AutomationML_BasicProperties.identification_AttributeTypeLib/semanticId",
    "BasePath": null,
    "LibraryName": "AutomationML_BasicProperties.identification_AttributeTypeLib",
    "LibraryVersion": "1.0.0",
    "AMLEdition": "AMLEd2",
    "ID": "3804f0c7-f80c-461f-930e-5d519f385ec5"
  },
  {
    "ClassName": "globalAssetId",
    "CaexPath": "RD_RDBasicProperties_AttributeTypeLib/globalAssetId",
    "BasePath": null,
    "LibraryName": "RD_RDBasicProperties_AttributeTypeLib",
    "LibraryVersion": "1.0.0",
    "AMLEdition": "AMLEd2",
    "ID": "f7932ea2-b7ee-427c-8848-3deb1a156f87"
  },
  {
    "ClassName": "globalAssetId",
    "CaexPath": "AutomationML_BasicProperties.identification_AttributeTypeLib/globalAssetId",
    "BasePath": null,
    "LibraryName": "AutomationML_BasicProperties.identification_AttributeTypeLib",
    "LibraryVersion": "1.0.0",
    "AMLEdition": "AMLEd2",
    "ID": "f7932ea2-b7ee-427c-8848-3deb1a156f87"
  },
  {
    "ClassName": "manufacturerName",
    "CaexPath": "RD_RDBasicProperties_AttributeTypeLib/manufacturerName",
    "BasePath": null,
    "LibraryName": "RD_RDBasicProperties_AttributeTypeLib",
    "LibraryVersion": "1.0.0",
    "AMLEdition": "AMLEd2",
    "ID": "5d973f74-2fb0-4b28-a517-b5bed8f77205"
  },
  {
    "ClassName": "manufacturerName",
    "CaexPath": "AutomationML_BasicProperties.identification_AttributeTypeLib/manufacturerName",
    "BasePath": null,
    "LibraryName": "AutomationML_BasicProperties.identification_AttributeTypeLib",
    "LibraryVersion": "1.0.0",
    "AMLEdition": "AMLEd2",
    "ID": "5d973f74-2fb0-4b28-a517-b5bed8f77205"
  },
  {
    "ClassName": "manufacturerProductDesignation",
    "CaexPath": "RD_RDBasicProperties_AttributeTypeLib/manufacturerProductDesignation",
    "BasePath": null,
    "LibraryName": "RD_RDBasicProperties_AttributeTypeLib",
    "LibraryVersion": "1.0.0",
    "AMLEdition": "AMLEd2",
    "ID": "81a61bac-b168-4a55-84c7-5251c2526611"
  },
  {
    "ClassName": "manufacturerProductDesignation",
    "CaexPath": "AutomationML_BasicProperties.identification_AttributeTypeLib/manufacturerProductDesignation",
    "BasePath": null,
    "LibraryName": "AutomationML_BasicProperties.identification_AttributeTypeLib",
    "LibraryVersion": "1.0.0",
    "AMLEdition": "AMLEd2",
    "ID": "81a61bac-b168-4a55-84c7-5251c2526611"
  },
  {
    "ClassName": "partNumber",
    "CaexPath": "RD_RDBasicProperties_AttributeTypeLib/partNumber",
    "BasePath": null,
    "LibraryName": "RD_RDBasicProperties_AttributeTypeLib",
    "LibraryVersion": "1.0.0",
    "AMLEdition": "AMLEd2",
    "ID": "4778e1b2-d9ec-4945-b5ed-4abd807e2d7e"
  },
  {
    "ClassName": "partNumber",
    "CaexPath": "AutomationML_BasicProperties.identification_AttributeTypeLib/partNumber",
    "BasePath": null,
    "LibraryName": "AutomationML_BasicProperties.identification_AttributeTypeLib",
    "LibraryVersion": "1.0.0",
    "AMLEdition": "AMLEd2",
    "ID": "4778e1b2-d9ec-4945-b5ed-4abd807e2d7e"
  },
  {
    "ClassName": "powerDemandMax",
    "CaexPath": "RD_RDBasicProperties.energyAndConsumption_AttributeTypeLib/powerDemandMax",
    "BasePath": null,
    "LibraryName": "RD_RDBasicProperties.energyAndConsumption_AttributeTypeLib",
    "LibraryVersion": "1.0.0",
    "AMLEdition": "AMLEd2",
    "ID": "cfcecbcc-f029-4d9c-95f5-a26d394a30af"
  },
  {
    "ClassName": "powerDemandMax",
    "CaexPath": "AutomationML_BasicProperties.energyAndConsumption_AttributeTypeLib/powerDemandMax",
    "BasePath": null,
    "LibraryName": "AutomationML_BasicProperties.energyAndConsumption_AttributeTypeLib",
    "LibraryVersion": "1.0.0",
    "AMLEdition": "AMLEd2",
    "ID": "cfcecbcc-f029-4d9c-95f5-a26d394a30af"
  },
  {
    "ClassName": "powerDemandIdle",
    "CaexPath": "RD_RDBasicProperties.energyAndConsumption_AttributeTypeLib/powerDemandIdle",
    "BasePath": null,
    "LibraryName": "RD_RDBasicProperties.energyAndConsumption_AttributeTypeLib",
    "LibraryVersion": "1.0.0",
    "AMLEdition": "AMLEd2",
    "ID": "797f704c-4124-439d-ae93-94efb710416e"
  },
  {
    "ClassName": "powerDemandIdle",
    "CaexPath": "AutomationML_BasicProperties.energyAndConsumption_AttributeTypeLib/powerDemandIdle",
    "BasePath": null,
    "LibraryName": "AutomationML_BasicProperties.energyAndConsumption_AttributeTypeLib",
    "LibraryVersion": "1.0.0",
    "AMLEdition": "AMLEd2",
    "ID": "797f704c-4124-439d-ae93-94efb710416e"
  },
  {
    "ClassName": "powerDemandStandby",
    "CaexPath": "RD_RDBasicProperties.energyAndConsumption_AttributeTypeLib/powerDemandStandby",
    "BasePath": null,
    "LibraryName": "RD_RDBasicProperties.energyAndConsumption_AttributeTypeLib",
    "LibraryVersion": "1.0.0",
    "AMLEdition": "AMLEd2",
    "ID": "1bcae9d2-c428-484e-8477-80ddbe6637e0"
  },
  {
    "ClassName": "powerDemandStandby",
    "CaexPath": "AutomationML_BasicProperties.energyAndConsumption_AttributeTypeLib/powerDemandStandby",
    "BasePath": null,
    "LibraryName": "AutomationML_BasicProperties.energyAndConsumption_AttributeTypeLib",
    "LibraryVersion": "1.0.0",
    "AMLEdition": "AMLEd2",
    "ID": "1bcae9d2-c428-484e-8477-80ddbe6637e0"
  },
  {
    "ClassName": "averagePowerDemand",
    "CaexPath": "RD_RDBasicProperties.energyAndConsumption_AttributeTypeLib/averagePowerDemand",
    "BasePath": null,
    "LibraryName": "RD_RDBasicProperties.energyAndConsumption_AttributeTypeLib",
    "LibraryVersion": "1.0.0",
    "AMLEdition": "AMLEd2",
    "ID": "99e71377-ab33-434b-b934-3dde1bbdb32f"
  },
  {
    "ClassName": "averagePowerDemand",
    "CaexPath": "AutomationML_BasicProperties.energyAndConsumption_AttributeTypeLib/averagePowerDemand",
    "BasePath": null,
    "LibraryName": "AutomationML_BasicProperties.energyAndConsumption_AttributeTypeLib",
    "LibraryVersion": "1.0.0",
    "AMLEdition": "AMLEd2",
    "ID": "99e71377-ab33-434b-b934-3dde1bbdb32f"
  },
  {
    "ClassName": "peakPowerDemand",
    "CaexPath": "RD_RDBasicProperties.energyAndConsumption_AttributeTypeLib/peakPowerDemand",
    "BasePath": null,
    "LibraryName": "RD_RDBasicProperties.energyAndConsumption_AttributeTypeLib",
    "LibraryVersion": "1.0.0",
    "AMLEdition": "AMLEd2",
    "ID": "aa85106c-f92f-4610-9d3b-ab9dc475380b"
  },
  {
    "ClassName": "peakPowerDemand",
    "CaexPath": "AutomationML_BasicProperties.energyAndConsumption_AttributeTypeLib/peakPowerDemand",
    "BasePath": null,
    "LibraryName": "AutomationML_BasicProperties.energyAndConsumption_AttributeTypeLib",
    "LibraryVersion": "1.0.0",
    "AMLEdition": "AMLEd2",
    "ID": "aa85106c-f92f-4610-9d3b-ab9dc475380b"
  },
  {
    "ClassName": "meanTimeToRepair",
    "CaexPath": "RD_RDBasicProperties.reliabilityAndLifetime_AttributeTypeLib/meanTimeToRepair",
    "BasePath": null,
    "LibraryName": "RD_RDBasicProperties.reliabilityAndLifetime_AttributeTypeLib",
    "LibraryVersion": "1.0.0",
    "AMLEdition": "AMLEd2",
    "ID": "867a8d4f-a01c-4258-8fd3-6d2d838421ce"
  },
  {
    "ClassName": "meanTimeToRepair",
    "CaexPath": "AutomationML_BasicProperties.reliabilityAndLifetime_AttributeTypeLib/meanTimeToRepair",
    "BasePath": null,
    "LibraryName": "AutomationML_BasicProperties.reliabilityAndLifetime_AttributeTypeLib",
    "LibraryVersion": "1.0.0",
    "AMLEdition": "AMLEd2",
    "ID": "867a8d4f-a01c-4258-8fd3-6d2d838421ce"
  },
  {
    "ClassName": "meanTimeToRestore",
    "CaexPath": "RD_RDBasicProperties.reliabilityAndLifetime_AttributeTypeLib/meanTimeToRestore",
    "BasePath": null,
    "LibraryName": "RD_RDBasicProperties.reliabilityAndLifetime_AttributeTypeLib",
    "LibraryVersion": "1.0.0",
    "AMLEdition": "AMLEd2",
    "ID": "975bad7e-af52-4759-8871-d72cbfcd764a"
  },
  {
    "ClassName": "meanTimeToRestore",
    "CaexPath": "AutomationML_BasicProperties.reliabilityAndLifetime_AttributeTypeLib/meanTimeToRestore",
    "BasePath": null,
    "LibraryName": "AutomationML_BasicProperties.reliabilityAndLifetime_AttributeTypeLib",
    "LibraryVersion": "1.0.0",
    "AMLEdition": "AMLEd2",
    "ID": "975bad7e-af52-4759-8871-d72cbfcd764a"
  },
  {
    "ClassName": "failureRate",
    "CaexPath": "RD_RDBasicProperties.reliabilityAndLifetime_AttributeTypeLib/failureRate",
    "BasePath": null,
    "LibraryName": "RD_RDBasicProperties.reliabilityAndLifetime_AttributeTypeLib",
    "LibraryVersion": "1.0.0",
    "AMLEdition": "AMLEd2",
    "ID": "e25a8bb5-fdfd-4f2a-949b-40c7c4b3eff9"
  },
  {
    "ClassName": "failureRate",
    "CaexPath": "AutomationML_BasicProperties.reliabilityAndLifetime_AttributeTypeLib/failureRate",
    "BasePath": null,
    "LibraryName": "AutomationML_BasicProperties.reliabilityAndLifetime_AttributeTypeLib",
    "LibraryVersion": "1.0.0",
    "AMLEdition": "AMLEd2",
    "ID": "e25a8bb5-fdfd-4f2a-949b-40c7c4b3eff9"
  },
  {
    "ClassName": "availability",
    "CaexPath": "RD_RDBasicProperties.reliabilityAndLifetime_AttributeTypeLib/availability",
    "BasePath": null,
    "LibraryName": "RD_RDBasicProperties.reliabilityAndLifetime_AttributeTypeLib",
    "LibraryVersion": "1.0.0",
    "AMLEdition": "AMLEd2",
    "ID": "2a3082df-f918-4ee7-bd9b-5507d3238825"
  },
  {
    "ClassName": "availability",
    "CaexPath": "AutomationML_BasicProperties.reliabilityAndLifetime_AttributeTypeLib/availability",
    "BasePath": null,
    "LibraryName": "AutomationML_BasicProperties.reliabilityAndLifetime_AttributeTypeLib",
    "LibraryVersion": "1.0.0",
    "AMLEdition": "AMLEd2",
    "ID": "2a3082df-f918-4ee7-bd9b-5507d3238825"
  },
  {
    "ClassName": "reliability",
    "CaexPath": "RD_RDBasicProperties.reliabilityAndLifetime_AttributeTypeLib/reliability",
    "BasePath": null,
    "LibraryName": "RD_RDBasicProperties.reliabilityAndLifetime_AttributeTypeLib",
    "LibraryVersion": "1.0.0",
    "AMLEdition": "AMLEd2",
    "ID": "17c0e861-8830-47f9-b6fa-eba01c712515"
  },
  {
    "ClassName": "reliability",
    "CaexPath": "AutomationML_BasicProperties.reliabilityAndLifetime_AttributeTypeLib/reliability",
    "BasePath": null,
    "LibraryName": "AutomationML_BasicProperties.reliabilityAndLifetime_AttributeTypeLib",
    "LibraryVersion": "1.0.0",
    "AMLEdition": "AMLEd2",
    "ID": "17c0e861-8830-47f9-b6fa-eba01c712515"
  },
  {
    "ClassName": "redundancyLevel",
    "CaexPath": "RD_RDBasicProperties.reliabilityAndLifetime_AttributeTypeLib/redundancyLevel",
    "BasePath": null,
    "LibraryName": "RD_RDBasicProperties.reliabilityAndLifetime_AttributeTypeLib",
    "LibraryVersion": "1.0.0",
    "AMLEdition": "AMLEd2",
    "ID": "8fb66270-4415-4df2-a417-c81fbdddb8d9"
  },
  {
    "ClassName": "redundancyLevel",
    "CaexPath": "AutomationML_BasicProperties.reliabilityAndLifetime_AttributeTypeLib/redundancyLevel",
    "BasePath": null,
    "LibraryName": "AutomationML_BasicProperties.reliabilityAndLifetime_AttributeTypeLib",
    "LibraryVersion": "1.0.0",
    "AMLEdition": "AMLEd2",
    "ID": "8fb66270-4415-4df2-a417-c81fbdddb8d9"
  },
  {
    "ClassName": "energyDemandPerCycle",
    "CaexPath": "RD_RDBasicProperties.energyAndConsumption_AttributeTypeLib/energyDemandPerCycle",
    "BasePath": null,
    "LibraryName": "RD_RDBasicProperties.energyAndConsumption_AttributeTypeLib",
    "LibraryVersion": "1.0.0",
    "AMLEdition": "AMLEd2",
    "ID": "6240c183-9043-4fd2-854d-a67ca47f05ef"
  },
  {
    "ClassName": "energyDemandPerCycle",
    "CaexPath": "AutomationML_BasicProperties.energyAndConsumption_AttributeTypeLib/energyDemandPerCycle",
    "BasePath": null,
    "LibraryName": "AutomationML_BasicProperties.energyAndConsumption_AttributeTypeLib",
    "LibraryVersion": "1.0.0",
    "AMLEdition": "AMLEd2",
    "ID": "6240c183-9043-4fd2-854d-a67ca47f05ef"
  },
  {
    "ClassName": "energyDemandPerHour",
    "CaexPath": "RD_RDBasicProperties.energyAndConsumption_AttributeTypeLib/energyDemandPerHour",
    "BasePath": null,
    "LibraryName": "RD_RDBasicProperties.energyAndConsumption_AttributeTypeLib",
    "LibraryVersion": "1.0.0",
    "AMLEdition": "AMLEd2",
    "ID": "74e9e8cf-a72c-46e2-b146-ae967e62174c"
  },
  {
    "ClassName": "energyDemandPerHour",
    "CaexPath": "AutomationML_BasicProperties.energyAndConsumption_AttributeTypeLib/energyDemandPerHour",
    "BasePath": null,
    "LibraryName": "AutomationML_BasicProperties.energyAndConsumption_AttributeTypeLib",
    "LibraryVersion": "1.0.0",
    "AMLEdition": "AMLEd2",
    "ID": "74e9e8cf-a72c-46e2-b146-ae967e62174c"
  },
  {
    "ClassName": "serialNumber",
    "CaexPath": "RD_RDBasicProperties_AttributeTypeLib/serialNumber",
    "BasePath": null,
    "LibraryName": "RD_RDBasicProperties_AttributeTypeLib",
    "LibraryVersion": "1.0.0",
    "AMLEdition": "AMLEd2",
    "ID": "81d2caa2-36ca-40f2-bc19-a266f691bf33"
  },
  {
    "ClassName": "serialNumber",
    "CaexPath": "AutomationML_BasicProperties.identification_AttributeTypeLib/serialNumber",
    "BasePath": null,
    "LibraryName": "AutomationML_BasicProperties.identification_AttributeTypeLib",
    "LibraryVersion": "1.0.0",
    "AMLEdition": "AMLEd2",
    "ID": "81d2caa2-36ca-40f2-bc19-a266f691bf33"
  },
  {
    "ClassName": "energyDemandPerDay",
    "CaexPath": "RD_RDBasicProperties.energyAndConsumption_AttributeTypeLib/energyDemandPerDay",
    "BasePath": null,
    "LibraryName": "RD_RDBasicProperties.energyAndConsumption_AttributeTypeLib",
    "LibraryVersion": "1.0.0",
    "AMLEdition": "AMLEd2",
    "ID": "df75f411-0a1a-4b19-ac89-4120a6d2da99"
  },
  {
    "ClassName": "energyDemandPerDay",
    "CaexPath": "AutomationML_BasicProperties.energyAndConsumption_AttributeTypeLib/energyDemandPerDay",
    "BasePath": null,
    "LibraryName": "AutomationML_BasicProperties.energyAndConsumption_AttributeTypeLib",
    "LibraryVersion": "1.0.0",
    "AMLEdition": "AMLEd2",
    "ID": "df75f411-0a1a-4b19-ac89-4120a6d2da99"
  },
  {
    "ClassName": "energyDemandPerYear",
    "CaexPath": "RD_RDBasicProperties.energyAndConsumption_AttributeTypeLib/energyDemandPerYear",
    "BasePath": null,
    "LibraryName": "RD_RDBasicProperties.energyAndConsumption_AttributeTypeLib",
    "LibraryVersion": "1.0.0",
    "AMLEdition": "AMLEd2",
    "ID": "d885da3f-405d-4a1a-a1ae-6f3212d8fee0"
  },
  {
    "ClassName": "energyDemandPerYear",
    "CaexPath": "AutomationML_BasicProperties.energyAndConsumption_AttributeTypeLib/energyDemandPerYear",
    "BasePath": null,
    "LibraryName": "AutomationML_BasicProperties.energyAndConsumption_AttributeTypeLib",
    "LibraryVersion": "1.0.0",
    "AMLEdition": "AMLEd2",
    "ID": "d885da3f-405d-4a1a-a1ae-6f3212d8fee0"
  },
  {
    "ClassName": "energyEfficiencyClass",
    "CaexPath": "RD_RDBasicProperties.energyAndConsumption_AttributeTypeLib/energyEfficiencyClass",
    "BasePath": null,
    "LibraryName": "RD_RDBasicProperties.energyAndConsumption_AttributeTypeLib",
    "LibraryVersion": "1.0.0",
    "AMLEdition": "AMLEd2",
    "ID": "91a9e21c-1e89-44d7-aa78-959bd6d9b918"
  },
  {
    "ClassName": "energyEfficiencyClass",
    "CaexPath": "AutomationML_BasicProperties.energyAndConsumption_AttributeTypeLib/energyEfficiencyClass",
    "BasePath": null,
    "LibraryName": "AutomationML_BasicProperties.energyAndConsumption_AttributeTypeLib",
    "LibraryVersion": "1.0.0",
    "AMLEdition": "AMLEd2",
    "ID": "91a9e21c-1e89-44d7-aa78-959bd6d9b918"
  },
  {
    "ClassName": "energyMeteringSupported",
    "CaexPath": "RD_RDBasicProperties.energyAndConsumption_AttributeTypeLib/energyMeteringSupported",
    "BasePath": null,
    "LibraryName": "RD_RDBasicProperties.energyAndConsumption_AttributeTypeLib",
    "LibraryVersion": "1.0.0",
    "AMLEdition": "AMLEd2",
    "ID": "735218ca-c284-4a6c-9333-dce1f94fd667"
  },
  {
    "ClassName": "energyMeteringSupported",
    "CaexPath": "AutomationML_BasicProperties.energyAndConsumption_AttributeTypeLib/energyMeteringSupported",
    "BasePath": null,
    "LibraryName": "AutomationML_BasicProperties.energyAndConsumption_AttributeTypeLib",
    "LibraryVersion": "1.0.0",
    "AMLEdition": "AMLEd2",
    "ID": "735218ca-c284-4a6c-9333-dce1f94fd667"
  }
]